{
 "mdsDat": {
 "x": [ -0.03152371, -0.05497613, 0.008897766, 0.07760208 ],
"y": [ 0.03952731, 0.007643818, -0.07753302, 0.03036189 ],
"topics": [ 1, 2, 3, 4 ],
"Freq": [ 25.00007, 25.00004, 24.99997, 24.99991 ],
"cluster": [        1,        1,        1,        1 ] 
},
"tinfo": {
 "Term": [ "people", "thousands", "economy", "tens", "vat", "speculators", "unemployment", "jobs", "government", "austerity", "immoral", "investment", "cuts", "benefit", "goods", "hand", "million", "british", "key", "market", "purchase", "savage", "taking", "promising", "hundreds", "previous", "dismally", "sustaining", "german", "unjust", "cuts", "people", "hand", "promising", "previous", "immoral", "squeeze", "speculators", "need", "social", "dictated", "acceptance", "add", "dismally", "utilise", "elsewhere", "risen", "pockets", "legislated", "government", "power", "lives", "much", "inadequate", "child", "hundreds", "market", "dole", "dislocation", "ecb", "sustaining", "tens", "unemployment", "abject", "thousands", "growth", "investment", "speculators", "export", "fine", "eu", "pockets", "hundreds", "funds", "trapped", "promising", "french", "show", "householders", "interest", "market", "banks", "period", "tired", "countries", "need", "austerity", "failure", "legislated", "dislocates", "british", "criminal", "economy", "frenzied", "agree", "unjust", "increases", "vassal", "downward", "scrapheap", "dismally", "bankers", "happening", "private", "fивil", "going", "diktats", "financial", "capitalist", "vat", "risen", "services", "real", "dictated", "immoral", "inadequate", "fine", "dislocation", "welcomed", "unfortunately", "benefit", "key", "relief", "savage", "decimating", "republic", "goods", "german", "vat", "otherwise", "million", "entered", "nightmare", "hand", "since", "much", "equity", "four", "previous", "period", "people", "dole", "disastrous", "budget", "capital", "incomes", "markets", "bail", "jobs", "now", "domestic", "thousands", "policy", "demand", "taking", "purchase", "jobs", "trapped", "slavishly", "policy", "unemployment", "irish", "А", "government", "slavishly", "irish", "irish", "domestic", "austerity", "means", "workers", "government", "austerity", "tens", "А", "taking", "banks", "financial", "purchase", "years", "economy", "years", "investment", "workers", "taking", "workers", "exports", "exports", "policy", "А", "irish", "jobs", "million", "investment", "services", "domestic", "purchase", "economy", "now", "exports", "banks", "demand", "thousands", "means" ],
"logprob": [       30,       29,       28,       27,       26,       25,       24,       23,       22,       21,       20,       19,       18,       17,       16,       15,       14,       13,       12,       11,       10,        9,        8,        7,        6,        5,        4,        3,        2,        1,  -4.4698,  -2.8347,  -4.8041,  -4.8181,  -4.8388,  -4.1781,   -4.909,  -4.2169,  -4.9397,  -4.9409,  -4.9507,   -4.954,  -4.9773,  -4.9871,  -4.9922,  -4.9942,  -4.9986,  -5.0395,  -5.0433,  -3.6726,  -5.0652,   -5.074,  -5.0753,  -5.0961,  -5.1035,  -4.4136,  -4.4167,  -5.1237,  -5.1462,  -5.1543,  -4.5743,   -3.587,  -3.6655,  -4.7856,  -3.0327,  -4.8511,   -3.753,  -4.1838,   -4.883,  -4.8903,  -4.8948,  -4.9173,   -4.242,  -4.9468,  -4.2667,  -4.9657,  -4.9814,  -4.9982,  -5.0025,  -5.0069,  -4.3295,  -3.9281,  -5.0322,  -5.0536,  -5.0599,  -5.0796,  -3.9815,  -5.0963,  -5.1112,  -5.1198,  -4.5006,  -4.6474,  -3.0538,  -4.7227,  -4.7239,  -4.7407,  -4.7549,  -4.8039,  -4.8378,  -4.8384,  -4.8428,  -4.8516,   -4.868,   -4.878,  -4.9401,  -4.9545,  -4.9648,  -4.2801,  -4.9801,  -4.2874,  -4.9961,  -4.3039,  -4.9972,  -5.0073,  -4.3306,  -5.0367,  -5.0405,   -5.048,  -5.0594,  -5.0628,  -4.4261,  -4.5504,  -4.6476,  -4.6661,  -4.6896,  -4.7166,  -4.0259,  -4.7317,  -4.0629,  -4.8325,  -4.1638,  -4.8866,  -4.1973,  -4.9063,  -4.9091,  -4.9296,   -4.945,  -4.9607,  -4.9765,  -4.9775,  -3.0376,  -4.9904,  -4.9955,  -4.9963,   -4.999,  -5.0012,  -5.0099,   -5.017,  -3.9225,  -4.3303,  -4.0228,  -3.3836,  -3.7639,  -4.3846,  -4.4838,  -4.3544,  -4.0225,  -4.4849,  -4.4066,  -3.8432,   -4.211,  -3.7518,    -4.12,  -3.9324,  -4.5542,  -3.7283,  -3.8654,  -4.1525,  -4.2516,  -4.5568,  -4.4926,  -4.0549,  -4.1941,  -4.1847,  -4.2002,  -4.4883,  -4.2998,  -4.4947,  -4.5058,  -4.5001,  -4.0289,   -4.524,  -4.3511,  -4.6571,  -4.6712,  -4.5772,  -4.6742,  -4.6229,  -4.3618,  -4.5319,  -4.3813,  -4.6261,  -4.7779,  -4.6154,   -4.803,  -4.6514,  -4.8421,  -4.6427,  -4.8428,   -4.807,  -4.7717,  -4.9256,  -4.7359,  -4.9168 ],
"loglift": [       30,       29,       28,       27,       26,       25,       24,       23,       22,       21,       20,       19,       18,       17,       16,       15,       14,       13,       12,       11,       10,        9,        8,        7,        6,        5,        4,        3,        2,        1,   1.0396,   0.7288,   0.7054,   0.6914,   0.6706,   0.6381,   0.6004,   0.5994,   0.5698,   0.5685,   0.5587,   0.5555,   0.5321,   0.5223,   0.5172,   0.5152,   0.5108,   0.4699,   0.4662,   0.4505,   0.4442,   0.4354,   0.4341,   0.4133,   0.4059,   0.4026,   0.3995,   0.3857,   0.3632,   0.3551,   0.9351,   0.8237,   0.7453,   0.7239,    0.685,   0.6582,   0.6578,   0.6325,   0.6263,   0.6191,   0.6146,   0.5921,   0.5743,   0.5626,   0.5495,   0.5438,    0.528,   0.5112,   0.5069,   0.5025,   0.4867,   0.4826,   0.4772,   0.4558,   0.4494,   0.4298,   0.4293,   0.4131,   0.3983,   0.3896,   1.0088,    0.862,   0.8461,   0.7866,   0.7854,   0.7686,   0.7545,   0.7055,   0.6716,    0.671,   0.6666,   0.6578,   0.6413,   0.6314,   0.5693,   0.5549,   0.5445,   0.5362,   0.5292,   0.5288,   0.5133,   0.5123,   0.5122,   0.5021,   0.4857,   0.4727,   0.4689,   0.4613,     0.45,   0.4466,   1.0832,    0.959,   0.8618,   0.8433,   0.8198,   0.7928,   0.7903,   0.7777,   0.7533,   0.6768,   0.6525,   0.6228,   0.6189,   0.6031,   0.6002,   0.5798,   0.5643,   0.5486,   0.5329,   0.5319,   0.5259,    0.519,   0.5139,   0.5131,   0.5104,   0.5082,   0.4995,   0.4923,   0.4883,   0.4859,   0.3879,   0.3341,   0.3592,   0.4316,   0.3325,   0.4619,   0.3883,   0.3314,   0.4096,   0.2799,   0.1998,   0.1482,   0.2907,   0.1907,   0.2621,   0.1716,   0.0345,   0.2583,   0.1592,   0.2594,   0.3236,   0.0682,   0.2167,   0.2261,   0.2105,    0.328,    0.111,   0.3215,   0.3104,   0.3161,   -0.129,   0.2922,   0.0597,   0.1591,   0.1451,   0.2391,    0.142,   0.1933,  -0.2387,  -0.1211,  -0.4814,  -0.2154,   0.0383,  -0.2046,   0.0132,  -0.2406,  -0.0258,  -0.7428,  -0.0265,   0.0092,  -0.3609,  -0.1094,  -1.0182,  -0.1006 ],
"Freq": [        6,        5,        5,        2,        2,        1,        2,        3,        3,        2,        1,        2,        0,        1,        2,        0,        2,        1,        1,        1,        2,        0,        1,        0,        1,        0,        1,        0,        0,        1, 0.7069965,    3.627, 0.5061309, 0.499092, 0.4888676, 0.9464598, 0.4556971, 0.9104896, 0.4419516, 0.4413918, 0.4371162, 0.4356714, 0.425608, 0.4214724, 0.4193107, 0.4184932, 0.4166692, 0.3999566, 0.3984537, 1.569142, 0.3897925, 0.3863959, 0.3859005, 0.3779514, 0.3751715, 0.7478674, 0.7455509, 0.3676484, 0.3594688, 0.3565794, 0.6368507,  1.70925, 1.580303, 0.5155842, 2.975432, 0.4828489, 1.447827, 0.9410891, 0.467692, 0.4643093, 0.4622303, 0.4519269, 0.887888, 0.4388149, 0.8661964, 0.4305948, 0.4238873, 0.4168221, 0.4150453, 0.4132135, 0.8134735, 1.215246, 0.4029026, 0.3943527, 0.3918586, 0.3842221, 1.152097,  0.37788, 0.3722989, 0.3690818, 0.6855921, 0.5919919, 2.913268, 0.5490186, 0.5483461, 0.5392298, 0.5316565, 0.5062314, 0.4893331, 0.4890624, 0.4868814, 0.4826529, 0.4747693, 0.4700493, 0.4417579, 0.4354466, 0.4309614, 0.8547348, 0.424424, 0.8484664, 0.4176868, 0.8345616, 0.4172503, 0.4130434, 0.8126125, 0.4010677, 0.3995718, 0.3965521, 0.3920895, 0.3907453, 0.7385684, 0.6522665, 0.5918674, 0.5810139, 0.567494, 0.5524074, 1.102027, 0.5441328, 1.062057, 0.4919259, 0.9601415, 0.466022, 0.9284747, 0.4569527, 0.4556484, 0.4463992, 0.4395821, 0.4327337, 0.4259487, 0.4255522, 2.960987, 0.4200978, 0.4179376, 0.4176151, 0.4164898, 0.4155597, 0.4119621, 0.4090392, 1.222134, 0.8128479, 1.105444, 2.094858, 1.432143, 0.7699035, 0.6972021, 0.7935289, 1.105861, 0.6964518, 0.7531366, 1.323037, 0.9158641, 1.449669, 1.003054, 1.210091, 0.6498172, 1.484044, 1.293906, 0.9710183, 0.8794064, 0.6480801, 0.6910795, 1.070586, 0.9314516, 0.9402817, 0.9257795, 0.6940503, 0.8380037, 0.6895901, 0.6820359, 0.6859177, 1.098736, 0.669694, 0.7961288, 0.5862464, 0.5780434, 0.6350352, 0.5762924, 0.6066251, 0.7876506, 0.6644629, 0.7724355, 0.6046849, 0.5195446, 0.6112275, 0.5066435, 0.5896136, 0.4872552, 0.5947489, 0.4869083, 0.5046383, 0.5227705, 0.4482112, 0.5418293, 0.4521503 ],
"Total": [        6,        5,        5,        2,        2,        1,        2,        3,        3,        2,        1,        2,        0,        1,        2,        0,        2,        1,        1,        1,        2,        0,        1,        0,        1,        0,        1,        0,        0,        1,  0.99996, 6.999841, 0.9999803, 0.999952, 0.9999809, 1.999994, 0.9999727, 1.999904, 0.9999647, 0.9999911, 1.000007, 0.9999741, 0.9999783, 1.000008, 0.9999847, 0.9999792, 0.9999985, 0.9999612, 0.9999653, 3.999948, 0.9999805, 0.9999916, 0.9999882, 1.000002, 0.9999966,  1.99993, 1.999946, 0.9999957, 1.000006, 0.9999865, 0.9999671,  2.99996, 2.999901, 0.9999785, 5.999782, 0.9999966, 2.999913, 1.999904, 1.000003, 1.000008,        1, 0.9999612,  1.99993, 1.000007, 1.999938, 0.999952, 0.9999868, 1.000006, 0.9999895, 0.9999939, 1.999946,  2.99994, 0.9999961, 0.999999, 1.000006, 0.9999647, 2.999965, 0.9999836, 0.9999653, 0.9999972, 1.000042, 1.000027, 5.000144, 1.000031, 1.000035, 1.000043, 1.000025, 1.000037, 1.000026,  1.00002, 1.000008, 1.000044, 1.000031, 1.000018, 1.000027, 1.000026, 1.000029, 2.000065, 1.000028, 2.000097, 0.9999985, 2.000033,  1.00003, 1.000007, 1.999994, 1.000002, 1.000008, 1.000006,  1.00001, 1.000016, 1.000015, 1.000008, 0.9999999, 0.9999951, 1.000005, 1.000013, 2.000043, 0.9999945, 2.000097, 1.000031, 2.000031, 1.000011,  2.00001, 0.9999803, 1.000034, 0.9999882, 1.000028, 1.000024, 0.9999809, 0.9999961, 6.999841, 0.9999957, 1.000012, 1.000008, 1.000017, 0.9999898, 1.000005, 1.000019, 3.000096, 2.000026, 3.000006, 5.999782, 3.999962, 2.000022, 1.999952, 2.000055, 3.000096, 1.999938, 2.000021, 3.999962, 2.999901, 5.000053, 3.000049, 3.999948, 2.000021, 5.000053, 5.000053, 3.000006, 2.999965, 1.999987, 2.000043, 3.999948, 2.999965,  2.99996, 3.000049, 1.999952,  2.99994, 2.000065, 2.000055,  2.00004, 5.000144,  2.00004, 2.999913, 2.000043, 1.999952, 2.000043, 2.000018, 2.000018, 3.999962, 3.000049, 5.000053, 3.000096, 2.000031, 2.999913, 2.000033, 3.000006, 2.000055, 5.000144, 2.000026, 2.000018,  2.99994, 2.000022, 5.999782, 1.999987 ],
"Category": [ "Default", "Default", "Default", "Default", "Default", "Default", "Default", "Default", "Default", "Default", "Default", "Default", "Default", "Default", "Default", "Default", "Default", "Default", "Default", "Default", "Default", "Default", "Default", "Default", "Default", "Default", "Default", "Default", "Default", "Default", "Topic1", "Topic1", "Topic1", "Topic1", "Topic1", "Topic1", "Topic1", "Topic1", "Topic1", "Topic1", "Topic1", "Topic1", "Topic1", "Topic1", "Topic1", "Topic1", "Topic1", "Topic1", "Topic1", "Topic1", "Topic1", "Topic1", "Topic1", "Topic1", "Topic1", "Topic1", "Topic1", "Topic1", "Topic1", "Topic1", "Topic2", "Topic2", "Topic2", "Topic2", "Topic2", "Topic2", "Topic2", "Topic2", "Topic2", "Topic2", "Topic2", "Topic2", "Topic2", "Topic2", "Topic2", "Topic2", "Topic2", "Topic2", "Topic2", "Topic2", "Topic2", "Topic2", "Topic2", "Topic2", "Topic2", "Topic2", "Topic2", "Topic2", "Topic2", "Topic2", "Topic3", "Topic3", "Topic3", "Topic3", "Topic3", "Topic3", "Topic3", "Topic3", "Topic3", "Topic3", "Topic3", "Topic3", "Topic3", "Topic3", "Topic3", "Topic3", "Topic3", "Topic3", "Topic3", "Topic3", "Topic3", "Topic3", "Topic3", "Topic3", "Topic3", "Topic3", "Topic3", "Topic3", "Topic3", "Topic3", "Topic4", "Topic4", "Topic4", "Topic4", "Topic4", "Topic4", "Topic4", "Topic4", "Topic4", "Topic4", "Topic4", "Topic4", "Topic4", "Topic4", "Topic4", "Topic4", "Topic4", "Topic4", "Topic4", "Topic4", "Topic4", "Topic4", "Topic4", "Topic4", "Topic4", "Topic4", "Topic4", "Topic4", "Topic4", "Topic4", "Topic2", "Topic1", "Topic2", "Topic3", "Topic1", "Topic4", "Topic3", "Topic1", "Topic3", "Topic4", "Topic1", "Topic3", "Topic4", "Topic3", "Topic1", "Topic4", "Topic2", "Topic4", "Topic1", "Topic1", "Topic3", "Topic2", "Topic3", "Topic4", "Topic3", "Topic4", "Topic1", "Topic4", "Topic3", "Topic4", "Topic1", "Topic3", "Topic1", "Topic2", "Topic2", "Topic4", "Topic2", "Topic3", "Topic1", "Topic2", "Topic1", "Topic2", "Topic1", "Topic4", "Topic1", "Topic3", "Topic2", "Topic2", "Topic2", "Topic4", "Topic4", "Topic1", "Topic3", "Topic2" ] 
},
"token.table": {
 "Term": [ "А", "А", "А", "abject", "agree", "austerity", "austerity", "austerity", "banks", "banks", "banks", "benefit", "british", "criminal", "cuts", "decimating", "demand", "domestic", "domestic", "domestic", "economy", "economy", "economy", "exports", "exports", "exports", "financial", "financial", "frenzied", "german", "goods", "government", "government", "government", "hand", "hundreds", "hundreds", "immoral", "immoral", "increases", "investment", "investment", "investment", "irish", "irish", "irish", "irish", "jobs", "jobs", "jobs", "key", "market", "market", "means", "million", "million", "nightmare", "now", "people", "people", "policy", "policy", "policy", "purchase", "purchase", "relief", "republic", "savage", "services", "services", "slavishly", "slavishly", "speculators", "speculators", "sustaining", "taking", "taking", "taking", "tens", "tens", "thousands", "thousands", "thousands", "trapped", "trapped", "unemployment", "unemployment", "unjust", "vassal", "vat", "vat", "workers", "workers", "workers", "years", "years" ],
"Topic": [ 2, 3, 4, 2, 3, 1, 2, 3, 1, 2, 4, 4, 3, 3, 1, 4, 3, 2, 3, 4, 1, 2, 3, 2, 3, 4, 3, 4, 3, 4, 4, 1, 2, 3, 1, 1, 2, 1, 3, 3, 1, 2, 4, 1, 2, 3, 4, 2, 3, 4, 4, 1, 2, 1, 1, 4, 4, 4, 1, 4, 1, 2, 4, 3, 4, 4, 4, 4, 1, 3, 1, 3, 1, 2, 2, 1, 2, 4, 2, 4, 1, 2, 3, 1, 2, 1, 2, 3, 3, 3, 4, 2, 3, 4, 3, 4 ],
"Freq": [ 0.3333279, 0.3333279, 0.3333279, 1.000021, 0.9999654, 0.3333372, 0.3333372, 0.3333372,  0.33334,  0.33334,  0.33334, 0.9999846, 0.9999579, 0.9999731,  1.00004, 0.9999951, 0.4999945, 0.3333326, 0.3333326, 0.3333326, 0.1999942, 0.1999942, 0.5999827, 0.4999955, 0.4999955, 0.4999955, 0.4999838, 0.4999838, 0.9999689, 1.000006, 0.4999893, 0.5000065, 0.2500032, 0.2500032,  1.00002, 0.5000175, 0.5000175, 0.5000014, 0.5000014, 0.9999751, 0.333343, 0.333343, 0.333343, 0.1999979, 0.1999979, 0.1999979, 0.1999979, 0.3333227, 0.3333227, 0.3333227, 0.9999923, 0.5000134, 0.5000134, 0.5000032, 0.4999923, 0.4999923, 0.4999975, 0.4999935, 0.5714416, 0.4285812, 0.2500024, 0.2500024, 0.2500024, 0.4999861, 0.4999861,        1, 0.9999871, 1.000005, 0.4999918, 0.4999918, 0.4999948, 0.4999948, 0.5000241, 0.5000241, 1.000033, 0.500012, 0.500012, 0.500012, 0.6666756, 0.3333378, 0.3333454, 0.5000181, 0.1666727, 0.5000155, 0.5000155, 0.3333443, 0.6666887, 0.9999566, 0.9999631, 0.4999758, 0.4999758, 0.4999892, 0.4999892, 0.4999892, 0.4999901, 0.4999901 ] 
},
"R":       30,
"lambda.step":     0.01,
"plot.opts": {
 "xlab": "PC1",
"ylab": "PC2" 
},
"topic.order": [ 1, 2, 3, 4 ] 
}